{
"Metadata": {
  "Version": "2",
  "Commit": "dc796dd241603dc1"
},
"Identify": {
  "Serial number": "S2BENCAHC05716J",
  "Firmware version": "EXM04B6Q",
  "Model number": "Samsung SSD 850 PRO 512GB",
  "Serial number long": "Samsung_SSD_850_PRO_512GB_S2BENCAHC05716J",
  "Size bytes": 512110190592,
  "HW sector bytes": 512,
  "Logical block bytes": 512,
  "Physical block bytes": 512,
  "Source": "udev"
},
"Discovery 0": {
  "TPer Feature": {
    "Version": 1,
    "ComID Mgmt Supported": 0,
    "Streaming Supported": 1,
    "Buffer Mgmt Supported": 0,
    "ACK/NAK Supported": 0,
    "Async Supported": 0,
    "Sync Supported": 1
  },
  "Locking Feature": {
    "Version": 1,
    "MBR Done": 0,
    "MBR Enabled": 0,
    "Media Encryption": 1,
    "Locked": 0,
    "Locking Enabled": 0,
    "Locking Supported": 1
  },
  "Geometry Feature": {
    "Version": 1,
    "ALIGN": 0,
    "LogicalBlockSize": 512,
    "AlignmentGranularity": 1,
    "LowestAlignedLBA": 0
  },
  "Opal SSC V2 Feature": {
    "Version": 1,
    "Minor Version": 0,
    "Base ComID": 4100,
    "Number of ComIDs": 1,
    "Range Crossing Behavior": 0,
    "Number of Locking SP Admin Authorities Supported": 4,
    "Number of Locking SP User Authorities Supported": 9,
    "Initial C_PIN_SID PIN Indicator": 0,
    "Behavior of C_PIN_SID PIN upon TPer Revert": 0
  },
  "Opal SSC V1 Feature": {
    "Version": 1,
    "Base ComID": 4100,
    "Number of ComIDs": 1,
    "Range Crossing": 0
  },
  "DataStore Table Feature": {
    "Version": 1,
    "Minor Version": 0,
    "Maximum number of DataStore tables": 9,
    "Maximum total size of DataStore tables": 10485760,
    "DataStore table size alignment": 1
  }},
"Discovery 1": {
  "Properties": {
    "MaxComPacketSize": "0x010200",
    "MaxResponseComPacketSize": "0x010200",
    "MaxPacketSize": "0x0101ec",
    "MaxIndTokenSize": "0x0101c8",
    "MaxPackets": "0x01",
    "MaxSubpackets": "0x01",
    "MaxMethods": "0x01",
    "MaxAuthentications": "0x05",
    "MaxSessions": "0x01",
    "MaxTransactionLimit": "0x01",
    "DefSessionTimeout": "0x00"
  }
},
"Discovery 2": {
  "0x0000020500000001": {
    "0x0000000100000000": {
      "0x0000000100000001": {
        "0x00": "0x0000000100000001",
        "0x04": "0x01",
        "0x0d": "0x00000000",
        "0x0e": "0x00000000"
      },
      "0x0000000100000002": {
        "0x00": "0x0000000100000002",
        "0x04": "0x01",
        "0x0d": "0x00000000",
        "0x0e": "0x00000000"
      },
      "0x0000000100000003": {
        "0x00": "0x0000000100000003",
        "0x04": "0x01",
        "0x0d": "0x00000000",
        "0x0e": "0x00000000"
      },
      "0x0000000100000006": {
        "0x00": "0x0000000100000006",
        "0x04": "0x01",
        "0x0d": "0x00000000",
        "0x0e": "0x00000000"
      },
      "0x0000000100000007": {
        "0x00": "0x0000000100000007",
        "0x04": "0x01",
        "0x0d": "0x00000000",
        "0x0e": "0x00000000"
      },
      "0x0000000100000008": {
        "0x00": "0x0000000100000008",
        "0x04": "0x01",
        "0x0d": "0x00000000",
        "0x0e": "0x00000000"
      },
      "0x0000000100000009": {
        "0x00": "0x0000000100000009",
        "0x04": "0x01",
        "0x0d": "0x00000000",
        "0x0e": "0x00000000"
      },
      "0x000000010000000b": {
        "0x00": "0x000000010000000b",
        "0x04": "0x01",
        "0x0d": "0x00000000",
        "0x0e": "0x00000000"
      },
      "0x0000000100000201": {
        "0x00": "0x0000000100000201",
        "0x04": "0x01",
        "0x0d": "0x00000000",
        "0x0e": "0x00000000"
      },
      "0x0000000100000204": {
        "0x00": "0x0000000100000204",
        "0x04": "0x01",
        "0x0d": "0x00000000",
        "0x0e": "0x00000000"
      },
      "0x0000000100000205": {
        "0x00": "0x0000000100000205",
        "0x04": "0x01",
        "0x0d": "0x00000000",
        "0x0e": "0x00000000"
      }
    },
    "0x0000000200000000": {
      "0x0000000200000001": {
        "0x00": "0x0000000200000001",
        "0x01": "0x0000020500000001",
        "0x05": "0x00000000",
        "0x06": "0x01"
      },
      "0x0000000200030001": {
      }
    },
    "0x0000000300000000": {
      "0x0000000300000001": {
        "0x00": "0x0000000300000001",
        "0x01": "0x0000020400000001",
        "0x03": "0x00000002"
      },
      "0x0000000300000002": {
        "0x00": "0x0000000300000002",
        "0x01": "0x0000020400000002",
        "0x03": "0x00000002"
      }
    },
    "0x0000000600000000": {
      "0x0000000600000008": {
        "0x00": "0x0000000600000008"
      },
      "0x000000060000000d": {
        "0x00": "0x000000060000000d"
      },
      "0x0000000600000016": {
        "0x00": "0x0000000600000016"
      },
      "0x0000000600000017": {
        "0x00": "0x0000000600000017"
      },
      "0x000000060000001c": {
        "0x00": "0x000000060000001c"
      },
      "0x0000000600000202": {
        "0x00": "0x0000000600000202"
      },
      "0x0000000600000203": {
        "0x00": "0x0000000600000203"
      },
      "0x0000000600000601": {
        "0x00": "0x0000000600000601"
      }
    },
    "0x0000000700000000": {
      "0x0000000700000001": {
      },
      "0x0000000700030001": {
      }
    },
    "0x0000000800000000": {
      "0x0000000800000001": {
        "0x00": "0x0000000800000001",
        "0x03": "[f2a400000c05a80000000900000001f3]",
        "0x04": "[]"
      },
      "0x0000000800000002": {
        "0x00": "0x0000000800000002",
        "0x03": "[f2a400000c05a80000000900000002f3]",
        "0x04": "[]"
      },
      "0x0000000800030001": {
        "0x00": "0x0000000800030001",
        "0x03": "[f2a400000c05a80000000900000006f3]",
        "0x04": "[05]"
      },
      "0x0000000800008c02": {
        "0x00": "0x0000000800008c02",
        "0x03": "[f2a400000c05a80000000900000002f3f2a400000c05a80000000900000006f3f2a40000040e01f3]",
        "0x04": "[0004050607]"
      },
      "0x0000000800008c03": {
        "0x00": "0x0000000800008c03",
        "0x03": "[f2a400000c05a80000000900000006f3]",
        "0x04": "[03]"
      },
      "0x0000000800008c04": {
        "0x00": "0x0000000800008c04",
        "0x03": "[f2a400000c05a80000000900000001f3]",
        "0x04": "[0003]"
      },
      "0x000000080003a001": {
        "0x00": "0x000000080003a001",
        "0x03": "[f2a400000c05a80000000900000002f3f2a400000c05a80000000900000006f3f2a40000040e01f3]",
        "0x04": "[03]"
      },
      "0x00000008000100e1": {
        "0x00": "0x00000008000100e1",
        "0x03": "[f2a400000c05a80000000900000001f3f2a400000c05a80000000900000006f3f2a40000040e01f3]",
        "0x04": "[0004050607]"
      },
      "0x0000000800030003": {
        "0x00": "0x0000000800030003",
        "0x03": "[f2a400000c05a80000000900000006f3]",
        "0x04": "[08]"
      },
      "0x0000000800030002": {
        "0x00": "0x0000000800030002",
        "0x03": "[f2a400000c05a80000000900000006f3]",
        "0x04": "[]"
      },
      "0x00000008000100e0": {
        "0x00": "0x00000008000100e0",
        "0x03": "[f2a400000c05a8000000090001ff01f3]",
        "0x04": "[]"
      }
    },
    "0x0000000900000000": {
      "0x0000000900000001": {
        "0x00": "0x0000000900000001",
        "0x02": "() 0x20",
        "0x03": "0x00",
        "0x04": "0x0000000000000000",
        "0x05": "0x01",
        "0x06": "0x00",
        "0x07": "0x00",
        "0x08": "0x00",
        "0x09": "0x00",
        "0x0a": "0x0000000000000000",
        "0x0b": "0x0000000000000000",
        "0x0c": "0x0000000000000000"
      },
      "0x0000000900000002": {
        "0x00": "0x0000000900000002",
        "0x02": "() 0x20",
        "0x03": "0x01",
        "0x04": "0x0000000000000000",
        "0x05": "0x01",
        "0x06": "0x00",
        "0x07": "0x00",
        "0x08": "0x00",
        "0x09": "0x00",
        "0x0a": "0x0000000000000000",
        "0x0b": "0x0000000000000000",
        "0x0c": "0x0000000000000000"
      },
      "0x0000000900000003": {
        "0x00": "0x0000000900000003",
        "0x02": "() 0x20",
        "0x03": "0x01",
        "0x04": "0x0000000000000000",
        "0x05": "0x01",
        "0x06": "0x00",
        "0x07": "0x00",
        "0x08": "0x00",
        "0x09": "0x00",
        "0x0a": "0x0000000000000000",
        "0x0b": "0x0000000000000000",
        "0x0c": "0x0000000000000000"
      },
      "0x0000000900000006": {
        "0x00": "0x0000000900000006",
        "0x02": "() 0x20",
        "0x03": "0x00",
        "0x04": "0x0000000000000000",
        "0x05": "0x01",
        "0x06": "0x00",
        "0x07": "0x00",
        "0x08": "0x00",
        "0x09": "0x01",
        "0x0a": "0x0000000b00000001",
        "0x0b": "0x0000000000000000",
        "0x0c": "0x0000000000000000"
      },
      "0x000000090001ff01": {
        "0x00": "0x000000090001ff01",
        "0x02": "(PhysicalDriveOwner) 0x506879736963616c44726976654f776e6572",
        "0x03": "0x00",
        "0x04": "0x0000000000000000",
        "0x05": "0x01",
        "0x06": "0x00",
        "0x07": "0x00",
        "0x08": "0x00",
        "0x09": "0x01",
        "0x0a": "0x0000000b0001ff01",
        "0x0b": "0x0000000000000000",
        "0x0c": "0x0000000000000000"
      },
      "0x0000000900000201": {
        "0x00": "0x0000000900000201",
        "0x02": "() 0x20",
        "0x03": "0x00",
        "0x04": "0x0000000900000002",
        "0x05": "0x00",
        "0x06": "0x00",
        "0x07": "0x00",
        "0x08": "0x00",
        "0x09": "0x01",
        "0x0a": "0x0000000b00000201",
        "0x0b": "0x0000000000000000",
        "0x0c": "0x0000000000000000"
      }
    },
    "0x0000000b00000000": {
      "0x0000000b00000001": {

      },
      "0x0000000b00008402": {
        "0x00": "0x0000000b00008402",
        "0x03": "(SAMSUNG_SSD_MSID) 0x53414d53554e475f5353445f4d534944"
      },
      "0x0000000b0001ff01": {
        "0x00": "0x0000000b0001ff01",
        "0x04": "0x0000000000000000",
        "0x05": "0x00000005",
        "0x06": "0x00000000",
        "0x07": "0x00"
      },
      "0x0000000b00000201": {

      }
    },
    "0x0000020100000000": {
      "0x0000020100000001": {
      },
      "0x0000020100030001": {
        "0x00": "0x0000020100030001",
        "0x02": "0x022300085000000000000000",
        "0x04": "0x42323030",
        "0x05": "0x00000001",
        "0x07": "[a44f70616c]",
        "0x08": "0x00"
      }
    },
    "0x0000020400000000": {
      "0x0000020400000001": {
        "0x00": "0x0000020400000001",
        "0x02": "0x00000001",
        "0x03": "0x0000",
        "0x04": "0x0000"
      },
      "0x0000020400000002": {
        "0x00": "0x0000020400000002",
        "0x02": "0x00000001",
        "0x03": "0x0001",
        "0x04": "0x0001"
      },
      "0x0000020400000006": {
        "0x00": "0x0000020400000006",
        "0x02": "0x00000001",
        "0x03": "0x0001",
        "0x04": "0x0001"
      }
    },
    "0x0000020500000000": {
      "0x0000020500000001": {
        "0x00": "0x0000020500000001",
        "0x06": "0x09",
        "0x07": "0x00"
      },
      "0x0000020500000002": {
        "0x00": "0x0000020500000002",
        "0x06": "0x08",
        "0x07": "0x00"
      }
    }
  },
  "0x0000020500000002": {
    }
},
"Discovery 2 manual": {
  "0x0000020100030001": {
        "0x00": "0x0000020100030001",
        "0x02": "0x022300085000000000000000",
        "0x04": "0x42323030",
        "0x05": "0x00000001",
        "0x07": "[a44f70616c]",
        "0x08": "0x00"
  },
  "0x0000110100000001": {
  }
},
"Random sample": [
  [
    "f112ded2d81d184bcb077b3c7ec994dc00347fa44958aaf211a110fcc09d5e62",
    "b6ee1f5d41c6490577303a9b493fed5fb87dcea6b96d3be536dade89d1b40106",
    "7fb927b5edff6bfb59c01684f9adc87a681d0a36822f0e7f38f85e4a35f9fc14",
    "1b5cc3a9ddd876f56e368ff62f2599992ab46e86611e4bbeda5d6d4de5f36596"
  ],
  [
    "fa18cde17145abb7b8778d720f5b72b293dfad7c746d2c42570685bd81e9119e",
    "a3debbeb14264728a0d508cd460823e642dcef9e8ccd4eb9fbd6f68300071f7d",
    "82401fc9cd273f82d90fac82476e3f91f2eee51646f03374d84f391872712174",
    "bc3e6edb0d43c68ce7f29994bd2de49cfa332413d48239ba6931007d13d47056"
  ],
  [
    "96c59ff79ca2eb8876fc256dfd8d24899826761b7a5c090c6ba48a925a6c2f7c",
    "cca00846f666de81adb6666ac46501303e214aab0496c530185ed5e6ff56994e",
    "47ad5c50f6298c126c587eab4f622d5013cc637acc018626f0802d653d9154a4",
    "dd35edc23edb76d5096b4fb1541c0158e47c390b0e534269254335386567c839"
  ],
  [
    "f1a0d2b8a4a61b84ad1779c4b8e012ba098e299bb1b7b1bba5218994b32fb35c",
    "4e98387ef81de4ee00d769bdf1d6128956d87f9498818941d20deeda37128d35",
    "f5f8bf1ac00958e184950800edff28d77d8b3be9b632dea1aa6c5a1a01c625f7",
    "b703b62eb8e11ef23c2412b941a78790022944f59b6ee7fc28d6972df292c96a"
  ]
]
}
